chaim/__init__.py
chaim/chaimmodule.py
chaim/errors.py
chaim/inifile.py
chaim/logging.py
chaim/utils.py
chaim-0.8.6.dist-info/LICENSE
chaim-0.8.6.dist-info/METADATA
chaim-0.8.6.dist-info/WHEEL
chaim-0.8.6.dist-info/top_level.txt
chaim-0.8.6.dist-info/RECORD
