Metadata-Version: 2.1
Name: chaim
Version: 0.8.6
Summary: Centrica Chaim AWS Accounts - Python Module
Home-page: https://github.com/ConnectedHomes/chaim/tree/master/module
Author: Chris Allison
Author-email: chris.allison@hivehome.com
License: UNKNOWN
Platform: UNKNOWN
Classifier: Development Status :: 4 - Beta
Classifier: Programming Language :: Python :: 3
Classifier: License :: OSI Approved :: GNU Lesser General Public License v3 or later (LGPLv3+)
Classifier: Operating System :: OS Independent
Requires-Python: >=3
Requires-Dist: requests
Requires-Dist: chardet
Requires-Dist: certifi
Requires-Dist: ccalogging
